{
  "local_products_of_nepal": [
    {
      "id": "np001",
      "name": "Pashmina Shawl",
      "category": "Textiles",
      "description": "Luxurious shawls made from the fine wool of Himalayan goats, known for their softness and warmth.",
      "origin": "Kathmandu",
      "price_usd": 199,
      "image_url": "../images/products/np001.jpg"
    },
    {
      "id": "np002",
      "name": "Thangka Painting",
      "category": "Art",
      "description": "Traditional Buddhist scroll paintings depicting deities and mandalas, used for meditation and religious purposes.",
      "origin": "Kathmandu Valley",
      "price_usd": 20,
      "image_url": "../images/products/np002.jpg"
    },
    {
      "id": "np003",
      "name": "Singing Bowl",
      "category": "Art",
      "description": "Metal bowls that produce harmonic sounds when struck, commonly used in meditation and healing practices.",
      "origin": "Bhaktapur",
      "price_usd": 350,
      "image_url": "../images/products/np003.png"
    },
    {
      "id": "np004",
      "name": "Khukuri Knife",
      "category": "Art",
      "description": "Traditional curved knife associated with the Gurkhas, symbolizing bravery and used both as a tool and weapon.",
      "origin": "Eastern Nepal",
      "price_usd": 160,
      "image_url": "../images/products/np004.jpg"
    },
    {
      "id": "np005",
      "name": "Rice Paper Journal",
      "category": "Home Decor",
      "description": "Handmade journals crafted from Lokta bark, featuring unique textures and natural appeal.",
      "origin": "Kathmandu",
      "price_usd": 3,
      "image_url": "../images/products/np005.jpg"
    },
    {
      "id": "np006",
      "name": "Yak Wool Blanket",
      "category": "Textiles",
      "description": "Warm and durable blankets made from the wool of Himalayan yaks, ideal for cold climates.",
      "origin": "Himalayan Region",
      "price_usd": 75,
      "image_url": "../images/products/np006.webp"
    },
    {
      "id": "np007",
      "name": "Tibetan Rug",
      "category": "Home Decor",
      "description": "Hand-knotted rugs made from sheep’s wool, featuring traditional patterns and craftsmanship.",
      "origin": "Patan",
      "price_usd": 300,
      "image_url": "../images/products/np007.webp"
    },
    {
      "id": "np008",
      "name": "Nepali Tea",
      "category": "Textiles",
      "description": "Aromatic tea varieties cultivated in the hilly regions, offering unique flavors and health benefits.",
      "origin": "Ilam",
      "price_usd": 10,
      "image_url": "../images/products/np008.webp"
    },
    {
      "id": "np009",
      "name": "Handmade Jewelry",
      "category": "Textiles",
      "description": "Ethnic jewelry crafted by local artisans, featuring intricate designs and traditional motifs.",
      "origin": "Kathmandu",
      "price_usd": 25,
      "image_url": "../images/products/np009.webp"
    },
    {
      "id": "np010",
      "name": "Lokta Paper Lamp",
      "category": "Home Decor",
      "description": "Decorative lamps made from handmade Lokta paper, adding a warm ambiance to any space.",
      "origin": "Pokhara",
      "price_usd": 5,
      "image_url": "../images/products/np010.webp"
    }
  ]
}
